pymirc/__init__.py
pymirc/fileio/__init__.py
pymirc/fileio/labelvol_to_rtstruct.py
pymirc/fileio/radioPharmaceuticalInfoSequence.py
pymirc/fileio/read_dicom.py
pymirc/fileio/read_rtstruct.py
pymirc/fileio/write_dicom.py
pymirc/image_operations/__init__.py
pymirc/image_operations/aff_transform.py
pymirc/image_operations/backward_3d_warp.py
pymirc/image_operations/binary_2d_image_to_contours.py
pymirc/image_operations/forward_3d_warp.py
pymirc/image_operations/grad.py
pymirc/image_operations/mincostpath.py
pymirc/image_operations/random_deformation_field.py
pymirc/image_operations/reorient.py
pymirc/image_operations/resample_cont_cont.py
pymirc/image_operations/resample_img_cont.py
pymirc/image_operations/rigid_registration.py
pymirc/image_operations/zoom3d.py
pymirc/metrics/__init__.py
pymirc/metrics/cost_functions.py
pymirc/viewer/__init__.py
pymirc/viewer/threeaxisviewer.py
pymirc-0.30.2.dist-info/LICENSE
pymirc-0.30.2.dist-info/METADATA
pymirc-0.30.2.dist-info/WHEEL
pymirc-0.30.2.dist-info/top_level.txt
pymirc-0.30.2.dist-info/RECORD
