Metadata-Version: 2.2
Name: pymirc
Version: 0.30.2
Summary: Python imaging utilities developed in the medical imaging research center of KU Leuven
Author: Georg Schramm, Tom Eelbode, Jeroen Bertels
Maintainer-email: Georg Schramm <georg.schramm@kuleuven.be>
License:                    GNU LESSER GENERAL PUBLIC LICENSE
Project-URL: Repository, https://github.com/gschramm/pymirc
Classifier: Programming Language :: Python :: 3
Classifier: License :: OSI Approved :: GNU Lesser General Public License v3 or later (LGPLv3+)
Classifier: Operating System :: OS Independent
Requires-Python: >=3.8
License-File: LICENSE
Requires-Dist: numpy>=1.15
Requires-Dist: scipy>=1.1
Requires-Dist: matplotlib>=2.2.2
Requires-Dist: pydicom>=2.0
Requires-Dist: scikit-image>=0.14
Requires-Dist: numba>=0.39
Requires-Dist: nibabel>=3.0
